{
  "project_info": {
    "project_number": "209630829624",
    "firebase_url": "https://chatapp2-164f2.firebaseio.com",
    "project_id": "chatapp2-164f2",
    "storage_bucket": "chatapp2-164f2.appspot.com"
  },
  "client": [
    {
      "client_info": {
        "mobilesdk_app_id": "1:209630829624:android:153ec0a611584114645acd",
        "android_client_info": {
          "package_name": "com.kdc.chatapp_2"
        }
      },
      "oauth_client": [
        {
          "client_id": "209630829624-j4vt1dmgr04u1h7ui5in5afaoiga7f3d.apps.googleusercontent.com",
          "client_type": 1,
          "android_info": {
            "package_name": "com.kdc.chatapp_2",
            "certificate_hash": "0f751a09a83881e0de06df197833c36af80d482b"
          }
        },
        {
          "client_id": "209630829624-5macueplan0op36fnonh2i5qghaeiv0t.apps.googleusercontent.com",
          "client_type": 3
        }
      ],
      "api_key": [
        {
          "current_key": "AIzaSyDLGuS9L5f3Orx3O1VBXchsSXPvgqLc70s"
        }
      ],
      "services": {
        "appinvite_service": {
          "other_platform_oauth_client": [
            {
              "client_id": "209630829624-5macueplan0op36fnonh2i5qghaeiv0t.apps.googleusercontent.com",
              "client_type": 3
            }
          ]
        }
      }
    }
  ],
  "configuration_version": "1"
}